sphinx_evas_theme/__init__.py
sphinx_evas_theme/breadcrumbs.html
sphinx_evas_theme/events.py
sphinx_evas_theme/footer.html
sphinx_evas_theme/layout.html
sphinx_evas_theme/quickstart.py
sphinx_evas_theme/search.html
sphinx_evas_theme/searchbox.html
sphinx_evas_theme/theme.conf
sphinx_evas_theme/versions.html
sphinx_evas_theme/docx_templates/style.docx
sphinx_evas_theme/latex_templates/docinfo.sty
sphinx_evas_theme/latex_templates/logo.pdf
sphinx_evas_theme/latex_templates/preamble.tex
sphinx_evas_theme/latex_templates/titlepage.tex
sphinx_evas_theme/latex_templates/fonts/DejaVuSans-Bold.ttf
sphinx_evas_theme/latex_templates/fonts/DejaVuSans-Oblique.ttf
sphinx_evas_theme/latex_templates/fonts/DejaVuSans.ttf
sphinx_evas_theme/latex_templates/fonts/SourceHanSansSC-Regular.otf
sphinx_evas_theme/locale/sphinx.pot
sphinx_evas_theme/locale/en/LC_MESSAGES/sphinx.mo
sphinx_evas_theme/locale/en/LC_MESSAGES/sphinx.po
sphinx_evas_theme/locale/zh_CN/LC_MESSAGES/sphinx.mo
sphinx_evas_theme/locale/zh_CN/LC_MESSAGES/sphinx.po
sphinx_evas_theme/static/favicon.ico
sphinx_evas_theme/static/logo.svg
sphinx_evas_theme/static/css/badge_only.css
sphinx_evas_theme/static/css/theme.css
sphinx_evas_theme/static/css/fonts/Roboto-Slab-Bold.woff
sphinx_evas_theme/static/css/fonts/Roboto-Slab-Bold.woff2
sphinx_evas_theme/static/css/fonts/Roboto-Slab-Regular.woff
sphinx_evas_theme/static/css/fonts/Roboto-Slab-Regular.woff2
sphinx_evas_theme/static/css/fonts/fontawesome-webfont.eot
sphinx_evas_theme/static/css/fonts/fontawesome-webfont.svg
sphinx_evas_theme/static/css/fonts/fontawesome-webfont.ttf
sphinx_evas_theme/static/css/fonts/fontawesome-webfont.woff
sphinx_evas_theme/static/css/fonts/fontawesome-webfont.woff2
sphinx_evas_theme/static/css/fonts/lato-bold-italic.woff
sphinx_evas_theme/static/css/fonts/lato-bold-italic.woff2
sphinx_evas_theme/static/css/fonts/lato-bold.woff
sphinx_evas_theme/static/css/fonts/lato-bold.woff2
sphinx_evas_theme/static/css/fonts/lato-normal-italic.woff
sphinx_evas_theme-2.1.1.dist-info/LICENSE
sphinx_evas_theme-2.1.1.dist-info/METADATA
sphinx_evas_theme-2.1.1.dist-info/WHEEL
sphinx_evas_theme-2.1.1.dist-info/entry_points.txt
sphinx_evas_theme-2.1.1.dist-info/top_level.txt
sphinx_evas_theme-2.1.1.dist-info/RECORD
