Metadata-Version: 2.1
Name: sphinx_evas_theme
Version: 2.1.1
Summary: The perfect html and pdf style by using Sphinx and latex
Home-page: https://github.com/ikiwihome/sphinx_evas_theme
Author: EVAS Intelligence Co., Ltd
Author-email: business@evas.ai
License: MIT
Project-URL: Homepage, https://sphinx-evas-theme.readthedocs.io/
Project-URL: Source Code, https://github.com/ikiwihome/sphinx_evas_theme
Project-URL: Issue Tracker, https://github.com/ikiwihome/sphinx_evas_theme/issues
Classifier: Framework :: Sphinx
Classifier: Framework :: Sphinx :: Theme
Classifier: Development Status :: 5 - Production/Stable
Classifier: License :: OSI Approved :: MIT License
Classifier: Environment :: Console
Classifier: Environment :: Web Environment
Classifier: Intended Audience :: Developers
Classifier: Programming Language :: Python :: 3
Classifier: Programming Language :: Python :: 3 :: Only
Classifier: Programming Language :: Python :: 3.6
Classifier: Programming Language :: Python :: 3.7
Classifier: Programming Language :: Python :: 3.8
Classifier: Programming Language :: Python :: 3.9
Classifier: Programming Language :: Python :: 3.10
Classifier: Programming Language :: Python :: 3.11
Classifier: Programming Language :: Python :: 3.12
Classifier: Operating System :: OS Independent
Classifier: Topic :: Documentation
Classifier: Topic :: Software Development :: Documentation
Requires-Python: >=3.6
License-File: LICENSE
Requires-Dist: sphinx <8,>=5
Requires-Dist: docutils >=0.20
Requires-Dist: sphinxcontrib-jquery <5,>=4
Requires-Dist: sphinx-markdown-tables >=0.0.17
Requires-Dist: sphinx-copybutton >=0.5
Requires-Dist: myst-parser >=2.0.0
Requires-Dist: sphinx-design >=0.5.0
Requires-Dist: sphinx-togglebutton >=0.3.2
Requires-Dist: sphinx-markdown-checkbox >=0.1.0
Requires-Dist: sphinx-autobuild >=2024.10.3
Requires-Dist: sphinxcontrib-mermaid >=0.9.2
Requires-Dist: sphinxcontrib-getthecode >=1.2.1
Requires-Dist: docxbuilder >=1.2.0
Provides-Extra: dev
Requires-Dist: transifex-client ; extra == 'dev'
Requires-Dist: sphinxcontrib-httpdomain ; extra == 'dev'
Requires-Dist: bump2version ; extra == 'dev'
Requires-Dist: wheel ; extra == 'dev'
